LICENSE
MANIFEST.in
README.rst
setup.cfg
setup.py
src/misc_test_utils/__init__.py
src/misc_test_utils/misc_test_utils.py
src/misc_test_utils/vault.py
src/misc_test_utils.egg-info/PKG-INFO
src/misc_test_utils.egg-info/not-zip-safe