Metadata-Version: 1.1
Name: misc-test-utils
Version: 0.2
Summary: Utility functions for running unit and integration tests. With a focus on domain models and MySQL databases.
Home-page: https://github.com/CuriBio/misc-test-utils
Author: Curi Bio
Author-email: contact@curibio.com
License: MIT
Platform: UNKNOWN
Classifier: Development Status :: 1 - Planning
Classifier: License :: OSI Approved :: MIT License
Classifier: Programming Language :: Python
Classifier: Programming Language :: Python :: 3
Classifier: Programming Language :: Python :: 3.7
Classifier: Programming Language :: Python :: 3.8
Classifier: Topic :: Utilities
